coopr.opt-2.12.2-py2.7-nspkg.pth
coopr/opt/__init__.py
coopr/opt/results_schema.py
coopr/opt/base/__init__.py
coopr/opt/base/convert.py
coopr/opt/base/error.py
coopr/opt/base/formats.py
coopr/opt/base/log_config.py
coopr/opt/base/opt_config.py
coopr/opt/base/problem.py
coopr/opt/base/results.py
coopr/opt/base/solvers.py
coopr/opt/blackbox/__init__.py
coopr/opt/blackbox/point.py
coopr/opt/blackbox/problem.py
coopr/opt/blackbox/problem_io.py
coopr/opt/blackbox/solver.py
coopr/opt/parallel/__init__.py
coopr/opt/parallel/async_solver.py
coopr/opt/parallel/local.py
coopr/opt/parallel/manager.py
coopr/opt/plugins/__init__.py
coopr/opt/plugins/colin_xml_io.py
coopr/opt/plugins/dakota_text_io.py
coopr/opt/plugins/res.py
coopr/opt/plugins/sol.py
coopr/opt/problem/__init__.py
coopr/opt/problem/ampl.py
coopr/opt/results/__init__.py
coopr/opt/results/container.py
coopr/opt/results/OSResults.py
coopr/opt/results/problem.py
coopr/opt/results/results_.py
coopr/opt/results/solution.py
coopr/opt/results/solver.py
coopr/opt/scripts/__init__.py
coopr/opt/scripts/driver.py
coopr/opt/scripts/pyro_mip_server.py
coopr/opt/solver/__init__.py
coopr/opt/solver/ilmcmd.py
coopr/opt/solver/shellcmd.py
coopr/opt/testing/__init__.py
coopr/opt/testing/pyunit.py
coopr/opt/tests/__init__.py
coopr/opt/tests/base/__init__.py
coopr/opt/tests/base/test_ampl.py
coopr/opt/tests/base/test_config.py
coopr/opt/tests/base/test_convert.py
coopr/opt/tests/base/test_factory.py
coopr/opt/tests/base/test_sol.py
coopr/opt/tests/base/test_soln.py
coopr/opt/tests/base/test_solver.py
coopr/opt/tests/blackbox/__init__.py
coopr/opt/tests/blackbox/test_parallel.py
coopr/opt/tests/blackbox/test_problem.py
coopr/opt/tests/blackbox/test_ps.py
coopr.opt-2.12.2.dist-info/DESCRIPTION.rst
coopr.opt-2.12.2.dist-info/entry_points.txt
coopr.opt-2.12.2.dist-info/METADATA
coopr.opt-2.12.2.dist-info/metadata.json
coopr.opt-2.12.2.dist-info/namespace_packages.txt
coopr.opt-2.12.2.dist-info/RECORD
coopr.opt-2.12.2.dist-info/top_level.txt
coopr.opt-2.12.2.dist-info/WHEEL
